corefetch.py
corefetch-1.0.0.dist-info/licenses/LICENSE
corefetch-1.0.0.dist-info/METADATA
corefetch-1.0.0.dist-info/WHEEL
corefetch-1.0.0.dist-info/entry_points.txt
corefetch-1.0.0.dist-info/top_level.txt
corefetch-1.0.0.dist-info/RECORD
