Metadata-Version: 2.4
Name: corefetch
Version: 1.0.0
Summary: A powerful and fast system insights CLI tool with Sharingan ASCII art
Home-page: https://github.com/yokaimsi/corefetch
Author: yokaimsi
Author-email: contact.now.itachi@gmail.com
Classifier: Programming Language :: Python :: 3
Classifier: License :: OSI Approved :: MIT License
Classifier: Operating System :: OS Independent
Requires-Python: >=3.7
License-File: LICENSE
Requires-Dist: psutil
Requires-Dist: requests
Dynamic: author
Dynamic: author-email
Dynamic: classifier
Dynamic: description
Dynamic: description-content-type
Dynamic: home-page
Dynamic: license-file
Dynamic: requires-dist
Dynamic: requires-python
Dynamic: summary
